{
  "built_at_utc": "2026-02-17T09:06:31Z",
  "date": "2026-02-15",
  "git_sha": "fd7c2279f1180401a8d52c9842b795f7a23d7fe2",
  "props": {
    "all_targets": {
      "hit_rate": null,
      "hits": 0,
      "total": 0
    },
    "closest_misses": null,
    "reaches_hit": null,
    "top_targets": {
      "hit_rate": null,
      "hits": 0,
      "total": 0
    }
  },
  "season_end_year": 2026,
  "sources": {
    "targets_postmortem": "data/targets_postmortem.json",
    "targets_snapshot": "logs/targets_snapshot_2026-02-15.json"
  }
}