{
  "built_at_utc": "2026-04-23T15:29:29Z",
  "date": "2026-04-22",
  "git_sha": "95ee98da2a7387e25e513d51e01b464bab811b16",
  "props": {
    "all_targets": {
      "hit_rate": 1.0,
      "hits": 1,
      "total": 1
    },
    "closest_misses": null,
    "reaches_hit": 1,
    "top_targets": {
      "hit_rate": 1.0,
      "hits": 1,
      "total": 1
    }
  },
  "season_end_year": 2026,
  "sources": {
    "targets_postmortem": "data/targets_postmortem.json",
    "targets_snapshot": "logs/targets_snapshot_2026-04-22.json"
  }
}