{
  "built_at_utc": "2026-02-27T14:32:17Z",
  "date": "2026-02-26",
  "git_sha": "4d071c7a1a132a9ceebcefa80d409dbd01c61e88",
  "props": {
    "all_targets": {
      "hit_rate": 0.8,
      "hits": 24,
      "total": 30
    },
    "closest_misses": 4,
    "reaches_hit": 5,
    "top_targets": {
      "hit_rate": 0.6666666666666666,
      "hits": 4,
      "total": 6
    }
  },
  "season_end_year": 2026,
  "sources": {
    "targets_postmortem": "data/targets_postmortem.json",
    "targets_snapshot": "logs/targets_snapshot_2026-02-26.json"
  }
}