[
  {
    "asof_date": "2026-03-18",
    "player_id": "4278039.0",
    "player_name": "Nickeil Alexander-Walker",
    "team_abbrev": "ATL",
    "opp": "DAL",
    "game_id": "401810861",
    "stat": "3pt",
    "threshold": 3,
    "hits": 8,
    "window_games": 10,
    "hit_rate": 0.8,
    "is_home_game": false,
    "rest_days": 1,
    "is_b2b": false,
    "share_trend_pp": 9.297306859806865,
    "share_trend_dir": "UP",
    "iqr_10": 1.75,
    "landmine_rate_10": null,
    "trap_risk": null
  },
  {
    "asof_date": "2026-03-18",
    "player_id": "4395625.0",
    "player_name": "RJ Barrett",
    "team_abbrev": "TOR",
    "opp": "CHI",
    "game_id": "401810857",
    "stat": "pts",
    "threshold": 20,
    "hits": 8,
    "window_games": 10,
    "hit_rate": 0.8,
    "is_home_game": false,
    "rest_days": 2,
    "is_b2b": false,
    "share_trend_pp": 4.724855199751249,
    "share_trend_dir": "UP",
    "iqr_10": 4.75,
    "landmine_rate_10": 0.0,
    "trap_risk": false
  },
  {
    "asof_date": "2026-03-18",
    "player_id": "4395625.0",
    "player_name": "RJ Barrett",
    "team_abbrev": "TOR",
    "opp": "CHI",
    "game_id": "401810857",
    "stat": "reb",
    "threshold": 6,
    "hits": 8,
    "window_games": 10,
    "hit_rate": 0.8,
    "is_home_game": false,
    "rest_days": 2,
    "is_b2b": false,
    "share_trend_pp": 0.9506057488341213,
    "share_trend_dir": "FLAT",
    "iqr_10": 0.75,
    "landmine_rate_10": 0.1,
    "trap_risk": false
  },
  {
    "asof_date": "2026-03-18",
    "player_id": "6583.0",
    "player_name": "Anthony Davis",
    "team_abbrev": "DAL",
    "opp": "ATL",
    "game_id": "401810861",
    "stat": "ast",
    "threshold": 2,
    "hits": 9,
    "window_games": 10,
    "hit_rate": 0.9,
    "is_home_game": true,
    "rest_days": 68,
    "is_b2b": false,
    "share_trend_pp": -1.474261509547735,
    "share_trend_dir": "FLAT",
    "iqr_10": 1.0,
    "landmine_rate_10": 0.0,
    "trap_risk": false
  },
  {
    "asof_date": "2026-03-18",
    "player_id": "4431736.0",
    "player_name": "Toumani Camara",
    "team_abbrev": "POR",
    "opp": "IND",
    "game_id": "401810856",
    "stat": "ast",
    "threshold": 2,
    "hits": 10,
    "window_games": 10,
    "hit_rate": 1.0,
    "is_home_game": false,
    "rest_days": 1,
    "is_b2b": false,
    "share_trend_pp": 1.7068741140156816,
    "share_trend_dir": "FLAT",
    "iqr_10": 1.0,
    "landmine_rate_10": 0.0,
    "trap_risk": false
  },
  {
    "asof_date": "2026-03-18",
    "player_id": "4711272.0",
    "player_name": "Reed Sheppard",
    "team_abbrev": "HOU",
    "opp": "LAL",
    "game_id": "401810862",
    "stat": "reb",
    "threshold": 2,
    "hits": 9,
    "window_games": 10,
    "hit_rate": 0.9,
    "is_home_game": true,
    "rest_days": 1,
    "is_b2b": false,
    "share_trend_pp": -0.1113455411775599,
    "share_trend_dir": "FLAT",
    "iqr_10": 1.75,
    "landmine_rate_10": 0.0,
    "trap_risk": false
  },
  {
    "asof_date": "2026-03-18",
    "player_id": "4397688.0",
    "player_name": "Trey Murphy III",
    "team_abbrev": "NO",
    "opp": "LAC",
    "game_id": "401810860",
    "stat": "ast",
    "threshold": 4,
    "hits": 8,
    "window_games": 10,
    "hit_rate": 0.8,
    "is_home_game": true,
    "rest_days": 1,
    "is_b2b": false,
    "share_trend_pp": 3.662017583990668,
    "share_trend_dir": "UP",
    "iqr_10": 2.75,
    "landmine_rate_10": 0.2,
    "trap_risk": false
  },
  {
    "asof_date": "2026-03-18",
    "player_id": "4397688.0",
    "player_name": "Trey Murphy III",
    "team_abbrev": "NO",
    "opp": "LAC",
    "game_id": "401810860",
    "stat": "3pt",
    "threshold": 3,
    "hits": 8,
    "window_games": 10,
    "hit_rate": 0.8,
    "is_home_game": true,
    "rest_days": 1,
    "is_b2b": false,
    "share_trend_pp": 5.709353146853147,
    "share_trend_dir": "UP",
    "iqr_10": 1.0,
    "landmine_rate_10": null,
    "trap_risk": null
  },
  {
    "asof_date": "2026-03-18",
    "player_id": "2991070.0",
    "player_name": "Jerami Grant",
    "team_abbrev": "POR",
    "opp": "IND",
    "game_id": "401810856",
    "stat": "3pt",
    "threshold": 2,
    "hits": 9,
    "window_games": 10,
    "hit_rate": 0.9,
    "is_home_game": false,
    "rest_days": 1,
    "is_b2b": false,
    "share_trend_pp": 4.251451163215875,
    "share_trend_dir": "UP",
    "iqr_10": 1.0,
    "landmine_rate_10": null,
    "trap_risk": null
  },
  {
    "asof_date": "2026-03-18",
    "player_id": "4869342.0",
    "player_name": "Dyson Daniels",
    "team_abbrev": "ATL",
    "opp": "DAL",
    "game_id": "401810861",
    "stat": "reb",
    "threshold": 6,
    "hits": 9,
    "window_games": 10,
    "hit_rate": 0.9,
    "is_home_game": false,
    "rest_days": 1,
    "is_b2b": false,
    "share_trend_pp": 5.346997301067607,
    "share_trend_dir": "UP",
    "iqr_10": 2.75,
    "landmine_rate_10": 0.0,
    "trap_risk": false
  },
  {
    "asof_date": "2026-03-18",
    "player_id": "4433255.0",
    "player_name": "Chet Holmgren",
    "team_abbrev": "OKC",
    "opp": "BKN",
    "game_id": "401810855",
    "stat": "reb",
    "threshold": 8,
    "hits": 9,
    "window_games": 10,
    "hit_rate": 0.9,
    "is_home_game": false,
    "rest_days": 0,
    "is_b2b": true,
    "share_trend_pp": 2.2361224161731945,
    "share_trend_dir": "UP",
    "iqr_10": 2.75,
    "landmine_rate_10": 0.1,
    "trap_risk": false
  },
  {
    "asof_date": "2026-03-18",
    "player_id": "6450.0",
    "player_name": "Kawhi Leonard",
    "team_abbrev": "LAC",
    "opp": "NO",
    "game_id": "401810860",
    "stat": "pts",
    "threshold": 25,
    "hits": 8,
    "window_games": 10,
    "hit_rate": 0.8,
    "is_home_game": false,
    "rest_days": 3,
    "is_b2b": false,
    "share_trend_pp": -0.323607584944241,
    "share_trend_dir": "FLAT",
    "iqr_10": 2.75,
    "landmine_rate_10": 0.0,
    "trap_risk": false
  },
  {
    "asof_date": "2026-03-18",
    "player_id": "5041939.0",
    "player_name": "Cooper Flagg",
    "team_abbrev": "DAL",
    "opp": "ATL",
    "game_id": "401810861",
    "stat": "ast",
    "threshold": 4,
    "hits": 9,
    "window_games": 10,
    "hit_rate": 0.9,
    "is_home_game": true,
    "rest_days": 1,
    "is_b2b": false,
    "share_trend_pp": 5.360268345308395,
    "share_trend_dir": "UP",
    "iqr_10": 1.75,
    "landmine_rate_10": 0.0,
    "trap_risk": false
  }
]