{
  "asof_date": "2026-03-22",
  "built_at_utc": "2026-03-22T14:51:57Z",
  "source": "rotowire",
  "POR": [
    {
      "name": "D. Lillard",
      "status": "OFS",
      "details": "D. Lillard (OFS)"
    },
    {
      "name": "J. Grant",
      "status": "QUES",
      "details": "J. Grant (Ques)"
    },
    {
      "name": "V. Krejci",
      "status": "QUES",
      "details": "V. Krejci (Ques)"
    },
    {
      "name": "S. Sharpe",
      "status": "OUT",
      "details": "S. Sharpe (Out)"
    },
    {
      "name": "P. Watson",
      "status": "QUES",
      "details": "P. Watson (Ques)"
    }
  ],
  "DEN": [
    {
      "name": "P. Watson",
      "status": "QUES",
      "details": "P. Watson (Ques)"
    }
  ],
  "BKN": [
    {
      "name": "Egor Demin",
      "status": "OFS",
      "details": "Egor Demin (OFS)"
    },
    {
      "name": "D. Sharpe",
      "status": "OFS",
      "details": "D. Sharpe (OFS)"
    },
    {
      "name": "T. Mann",
      "status": "PROB",
      "details": "T. Mann (Prob)"
    },
    {
      "name": "N. Claxton",
      "status": "OUT",
      "details": "N. Claxton (Out)"
    },
    {
      "name": "N. Clowney",
      "status": "OUT",
      "details": "N. Clowney (Out)"
    },
    {
      "name": "M. Porter",
      "status": "OUT",
      "details": "M. Porter (Out)"
    },
    {
      "name": "D. Eubanks",
      "status": "OFS",
      "details": "D. Eubanks (OFS)"
    },
    {
      "name": "D. Hunter",
      "status": "OFS",
      "details": "D. Hunter (OFS)"
    },
    {
      "name": "Z. LaVine",
      "status": "OFS",
      "details": "Z. LaVine (OFS)"
    },
    {
      "name": "D. Sabonis",
      "status": "OFS",
      "details": "D. Sabonis (OFS)"
    },
    {
      "name": "D. Plowden",
      "status": "QUES",
      "details": "D. Plowden (Ques)"
    },
    {
      "name": "K. Murray",
      "status": "OUT",
      "details": "K. Murray (Out)"
    },
    {
      "name": "I. Stevens",
      "status": "OUT",
      "details": "I. Stevens (Out)"
    },
    {
      "name": "R. Westbrook",
      "status": "OUT",
      "details": "R. Westbrook (Out)"
    }
  ],
  "SAC": [
    {
      "name": "D. Eubanks",
      "status": "OFS",
      "details": "D. Eubanks (OFS)"
    },
    {
      "name": "D. Hunter",
      "status": "OFS",
      "details": "D. Hunter (OFS)"
    },
    {
      "name": "Z. LaVine",
      "status": "OFS",
      "details": "Z. LaVine (OFS)"
    },
    {
      "name": "D. Sabonis",
      "status": "OFS",
      "details": "D. Sabonis (OFS)"
    },
    {
      "name": "D. Plowden",
      "status": "QUES",
      "details": "D. Plowden (Ques)"
    },
    {
      "name": "K. Murray",
      "status": "OUT",
      "details": "K. Murray (Out)"
    },
    {
      "name": "I. Stevens",
      "status": "OUT",
      "details": "I. Stevens (Out)"
    },
    {
      "name": "R. Westbrook",
      "status": "OUT",
      "details": "R. Westbrook (Out)"
    }
  ],
  "WAS": [
    {
      "name": "C. Whitmore",
      "status": "OFS",
      "details": "C. Whitmore (OFS)"
    },
    {
      "name": "T. Johnson",
      "status": "QUES",
      "details": "T. Johnson (Ques)"
    },
    {
      "name": "L. Black",
      "status": "DOUBT",
      "details": "L. Black (Doubt)"
    },
    {
      "name": "T. Young",
      "status": "DOUBT",
      "details": "T. Young (Doubt)"
    },
    {
      "name": "A. Davis",
      "status": "OUT",
      "details": "A. Davis (Out)"
    },
    {
      "name": "K. George",
      "status": "OUT",
      "details": "K. George (Out)"
    },
    {
      "name": "D. Russell",
      "status": "OUT",
      "details": "D. Russell (Out)"
    },
    {
      "name": "J. Hart",
      "status": "QUES",
      "details": "J. Hart (Ques)"
    },
    {
      "name": "M. McBride",
      "status": "OUT",
      "details": "M. McBride (Out)"
    },
    {
      "name": "L. Shamet",
      "status": "OUT",
      "details": "L. Shamet (Out)"
    }
  ],
  "NYK": [
    {
      "name": "J. Hart",
      "status": "QUES",
      "details": "J. Hart (Ques)"
    },
    {
      "name": "M. McBride",
      "status": "OUT",
      "details": "M. McBride (Out)"
    },
    {
      "name": "L. Shamet",
      "status": "OUT",
      "details": "L. Shamet (Out)"
    }
  ],
  "MIN": [
    {
      "name": "N. Reid",
      "status": "QUES",
      "details": "N. Reid (Ques)"
    },
    {
      "name": "A. Edwards",
      "status": "OUT",
      "details": "A. Edwards (Out)"
    },
    {
      "name": "J. Brown",
      "status": "PROB",
      "details": "J. Brown (Prob)"
    },
    {
      "name": "N. Vucevic",
      "status": "OUT",
      "details": "N. Vucevic (Out)"
    }
  ],
  "BOS": [
    {
      "name": "J. Brown",
      "status": "PROB",
      "details": "J. Brown (Prob)"
    },
    {
      "name": "N. Vucevic",
      "status": "OUT",
      "details": "N. Vucevic (Out)"
    }
  ],
  "TOR": [
    {
      "name": "C. Murray-Boyles",
      "status": "QUES",
      "details": "C. Murray-Boyles (Ques)"
    },
    {
      "name": "C. Hepburn",
      "status": "OUT",
      "details": "C. Hepburn (Out)"
    },
    {
      "name": "R. O'Neale",
      "status": "QUES",
      "details": "R. O'Neale (Ques)"
    },
    {
      "name": "G. Allen",
      "status": "QUES",
      "details": "G. Allen (Ques)"
    },
    {
      "name": "A. Coffey",
      "status": "QUES",
      "details": "A. Coffey (Ques)"
    },
    {
      "name": "H. Highsmith",
      "status": "QUES",
      "details": "H. Highsmith (Ques)"
    },
    {
      "name": "D. Brooks",
      "status": "OUT",
      "details": "D. Brooks (Out)"
    },
    {
      "name": "M. Williams",
      "status": "OUT",
      "details": "M. Williams (Out)"
    }
  ],
  "PHX": [
    {
      "name": "G. Allen",
      "status": "QUES",
      "details": "G. Allen (Ques)"
    },
    {
      "name": "A. Coffey",
      "status": "QUES",
      "details": "A. Coffey (Ques)"
    },
    {
      "name": "H. Highsmith",
      "status": "QUES",
      "details": "H. Highsmith (Ques)"
    },
    {
      "name": "R. O'Neale",
      "status": "QUES",
      "details": "R. O'Neale (Ques)"
    },
    {
      "name": "D. Brooks",
      "status": "OUT",
      "details": "D. Brooks (Out)"
    },
    {
      "name": "M. Williams",
      "status": "OUT",
      "details": "M. Williams (Out)"
    }
  ]
}