{
  "asof_date": "2026-04-04",
  "built_at_utc": "2026-04-04T23:34:28Z",
  "source": "rotowire",
  "SAS": [
    {
      "name": "D. Jones Garcia",
      "status": "OFS",
      "details": "D. Jones Garcia (OFS)"
    },
    {
      "name": "E. Miller",
      "status": "OUT",
      "details": "E. Miller (Out)"
    },
    {
      "name": "Probable Pitchers",
      "status": "PROB",
      "details": "Probable Pitchers (Prob)"
    },
    {
      "name": "B. Brown",
      "status": "QUES",
      "details": "B. Brown (Ques)"
    },
    {
      "name": "S. Jones",
      "status": "OUT",
      "details": "S. Jones (Out)"
    },
    {
      "name": "Zeke Nnaji",
      "status": "OUT",
      "details": "Zeke Nnaji (Out)"
    },
    {
      "name": "P. Watson",
      "status": "OUT",
      "details": "P. Watson (Out)"
    }
  ],
  "DEN": [
    {
      "name": "B. Brown",
      "status": "QUES",
      "details": "B. Brown (Ques)"
    },
    {
      "name": "S. Jones",
      "status": "OUT",
      "details": "S. Jones (Out)"
    },
    {
      "name": "Zeke Nnaji",
      "status": "OUT",
      "details": "Zeke Nnaji (Out)"
    },
    {
      "name": "P. Watson",
      "status": "OUT",
      "details": "P. Watson (Out)"
    }
  ],
  "WAS": [
    {
      "name": "K. George",
      "status": "OFS",
      "details": "K. George (OFS)"
    },
    {
      "name": "C. Whitmore",
      "status": "OFS",
      "details": "C. Whitmore (OFS)"
    },
    {
      "name": "A. Davis",
      "status": "OUT",
      "details": "A. Davis (Out)"
    },
    {
      "name": "D. Russell",
      "status": "OUT",
      "details": "D. Russell (Out)"
    },
    {
      "name": "Alex Sarr",
      "status": "OUT",
      "details": "Alex Sarr (Out)"
    },
    {
      "name": "T. Vukcevic",
      "status": "OUT",
      "details": "T. Vukcevic (Out)"
    },
    {
      "name": "Trae Young",
      "status": "OUT",
      "details": "Trae Young (Out)"
    },
    {
      "name": "T. Herro",
      "status": "OUT",
      "details": "T. Herro (Out)"
    },
    {
      "name": "N. Powell",
      "status": "OUT",
      "details": "N. Powell (Out)"
    },
    {
      "name": "T. Rozier",
      "status": "OUT",
      "details": "T. Rozier (Out)"
    }
  ],
  "MIA": [
    {
      "name": "T. Herro",
      "status": "OUT",
      "details": "T. Herro (Out)"
    },
    {
      "name": "N. Powell",
      "status": "OUT",
      "details": "N. Powell (Out)"
    },
    {
      "name": "T. Rozier",
      "status": "OUT",
      "details": "T. Rozier (Out)"
    }
  ],
  "DET": [
    {
      "name": "C. Cunningham",
      "status": "OUT",
      "details": "C. Cunningham (Out)"
    },
    {
      "name": "I. Stewart",
      "status": "OUT",
      "details": "I. Stewart (Out)"
    },
    {
      "name": "J. Broome",
      "status": "OUT",
      "details": "J. Broome (Out)"
    },
    {
      "name": "J. Embiid",
      "status": "OUT",
      "details": "J. Embiid (Out)"
    }
  ],
  "PHI": [
    {
      "name": "J. Broome",
      "status": "OUT",
      "details": "J. Broome (Out)"
    },
    {
      "name": "J. Embiid",
      "status": "OUT",
      "details": "J. Embiid (Out)"
    }
  ]
}