{
  "asof_date": "2026-05-02",
  "built_at_utc": "2026-05-02T22:51:52Z",
  "source": "rotowire",
  "PHI": [
    {
      "name": "J. Embiid",
      "status": "PROB",
      "details": "J. Embiid (Prob)"
    },
    {
      "name": "Probable Pitchers",
      "status": "PROB",
      "details": "Probable Pitchers (Prob)"
    },
    {
      "name": "J. Tatum",
      "status": "OUT",
      "details": "J. Tatum (Out)"
    }
  ],
  "BOS": [
    {
      "name": "J. Tatum",
      "status": "OUT",
      "details": "J. Tatum (Out)"
    }
  ]
}