{
  "asof_date": "2026-01-09",
  "built_at_utc": "2026-01-10T02:46:30Z",
  "source": "rotowire",
  "TOR": [
    {
      "name": "R. Barrett",
      "status": "QUES",
      "details": "R. Barrett (Ques)"
    },
    {
      "name": "S. Barnes",
      "status": "OUT",
      "details": "S. Barnes (Out)"
    },
    {
      "name": "C. Hepburn",
      "status": "OUT",
      "details": "C. Hepburn (Out)"
    },
    {
      "name": "B. Ingram",
      "status": "OUT",
      "details": "B. Ingram (Out)"
    },
    {
      "name": "J. Poeltl",
      "status": "OUT",
      "details": "J. Poeltl (Out)"
    },
    {
      "name": "Fantasy Home",
      "status": "REST",
      "details": "Fantasy Home (Rest)"
    },
    {
      "name": "Fantasy Home",
      "status": "OUT",
      "details": "Fantasy Home (Out)"
    },
    {
      "name": "Fantasy Home",
      "status": "PROB",
      "details": "Fantasy Home (Prob)"
    },
    {
      "name": "Fantasy Football",
      "status": "REST",
      "details": "Fantasy Football (Rest)"
    },
    {
      "name": "J. Minott",
      "status": "OUT",
      "details": "J. Minott (Out)"
    },
    {
      "name": "J. Tatum",
      "status": "OUT",
      "details": "J. Tatum (Out)"
    }
  ],
  "BOS": [
    {
      "name": "J. Minott",
      "status": "OUT",
      "details": "J. Minott (Out)"
    },
    {
      "name": "J. Tatum",
      "status": "OUT",
      "details": "J. Tatum (Out)"
    }
  ],
  "ORL": [
    {
      "name": "C. Castleton",
      "status": "OUT",
      "details": "C. Castleton (Out)"
    },
    {
      "name": "T. da Silva",
      "status": "OUT",
      "details": "T. da Silva (Out)"
    },
    {
      "name": "J. Suggs",
      "status": "OUT",
      "details": "J. Suggs (Out)"
    },
    {
      "name": "M. Wagner",
      "status": "OUT",
      "details": "M. Wagner (Out)"
    },
    {
      "name": "F. Wagner",
      "status": "OUT",
      "details": "F. Wagner (Out)"
    }
  ],
  "NOP": [
    {
      "name": "J. Alvarado",
      "status": "OUT",
      "details": "J. Alvarado (Out)"
    },
    {
      "name": "Saddiq Bey",
      "status": "OUT",
      "details": "Saddiq Bey (Out)"
    },
    {
      "name": "H. Jones",
      "status": "OUT",
      "details": "H. Jones (Out)"
    },
    {
      "name": "D. Murray",
      "status": "OUT",
      "details": "D. Murray (Out)"
    },
    {
      "name": "C. Whitmore",
      "status": "OUT",
      "details": "C. Whitmore (Out)"
    },
    {
      "name": "Trae Young",
      "status": "OUT",
      "details": "Trae Young (Out)"
    }
  ],
  "WAS": [
    {
      "name": "C. Whitmore",
      "status": "OUT",
      "details": "C. Whitmore (Out)"
    },
    {
      "name": "Trae Young",
      "status": "OUT",
      "details": "Trae Young (Out)"
    }
  ],
  "LAC": [
    {
      "name": "B. Beal",
      "status": "OFS",
      "details": "B. Beal (OFS)"
    },
    {
      "name": "B. Bogdanovic",
      "status": "OUT",
      "details": "B. Bogdanovic (Out)"
    },
    {
      "name": "D. Jones",
      "status": "OUT",
      "details": "D. Jones (Out)"
    },
    {
      "name": "Chris Paul",
      "status": "OUT",
      "details": "Chris Paul (Out)"
    },
    {
      "name": "H. Highsmith",
      "status": "OUT",
      "details": "H. Highsmith (Out)"
    },
    {
      "name": "E. Liddell",
      "status": "OUT",
      "details": "E. Liddell (Out)"
    },
    {
      "name": "Ben Saraf",
      "status": "OUT",
      "details": "Ben Saraf (Out)"
    }
  ],
  "BKN": [
    {
      "name": "H. Highsmith",
      "status": "OUT",
      "details": "H. Highsmith (Out)"
    },
    {
      "name": "E. Liddell",
      "status": "OUT",
      "details": "E. Liddell (Out)"
    },
    {
      "name": "Ben Saraf",
      "status": "OUT",
      "details": "Ben Saraf (Out)"
    }
  ],
  "OKC": [
    {
      "name": "T. Sorber",
      "status": "OFS",
      "details": "T. Sorber (OFS)"
    },
    {
      "name": "S. Gilgeous-Alexander",
      "status": "OUT",
      "details": "S. Gilgeous-Alexander (Out)"
    },
    {
      "name": "I. Hartenstein",
      "status": "OUT",
      "details": "I. Hartenstein (Out)"
    },
    {
      "name": "C. Holmgren",
      "status": "OUT",
      "details": "C. Holmgren (Out)"
    },
    {
      "name": "N. Topic",
      "status": "OUT",
      "details": "N. Topic (Out)"
    },
    {
      "name": "C. Wallace",
      "status": "OUT",
      "details": "C. Wallace (Out)"
    },
    {
      "name": "J. Williams",
      "status": "OUT",
      "details": "J. Williams (Out)"
    },
    {
      "name": "K. Caldwell-Pope",
      "status": "DOUBT",
      "details": "K. Caldwell-Pope (Doubt)"
    },
    {
      "name": "B. Clarke",
      "status": "OUT",
      "details": "B. Clarke (Out)"
    },
    {
      "name": "Zach Edey",
      "status": "OUT",
      "details": "Zach Edey (Out)"
    },
    {
      "name": "Ty Jerome",
      "status": "OUT",
      "details": "Ty Jerome (Out)"
    },
    {
      "name": "J. Konchar",
      "status": "OUT",
      "details": "J. Konchar (Out)"
    },
    {
      "name": "Ja Morant",
      "status": "OUT",
      "details": "Ja Morant (Out)"
    },
    {
      "name": "S. Pippen",
      "status": "OUT",
      "details": "S. Pippen (Out)"
    }
  ],
  "MEM": [
    {
      "name": "K. Caldwell-Pope",
      "status": "DOUBT",
      "details": "K. Caldwell-Pope (Doubt)"
    },
    {
      "name": "B. Clarke",
      "status": "OUT",
      "details": "B. Clarke (Out)"
    },
    {
      "name": "Zach Edey",
      "status": "OUT",
      "details": "Zach Edey (Out)"
    },
    {
      "name": "Ty Jerome",
      "status": "OUT",
      "details": "Ty Jerome (Out)"
    },
    {
      "name": "J. Konchar",
      "status": "OUT",
      "details": "J. Konchar (Out)"
    },
    {
      "name": "Ja Morant",
      "status": "OUT",
      "details": "Ja Morant (Out)"
    },
    {
      "name": "S. Pippen",
      "status": "OUT",
      "details": "S. Pippen (Out)"
    }
  ],
  "ATL": [
    {
      "name": "N. Dante",
      "status": "OFS",
      "details": "N. Dante (OFS)"
    },
    {
      "name": "C. Kispert",
      "status": "OUT",
      "details": "C. Kispert (Out)"
    },
    {
      "name": "C. McCollum",
      "status": "OUT",
      "details": "C. McCollum (Out)"
    },
    {
      "name": "K. Porzingis",
      "status": "OUT",
      "details": "K. Porzingis (Out)"
    },
    {
      "name": "Z. Risacher",
      "status": "OUT",
      "details": "Z. Risacher (Out)"
    },
    {
      "name": "T. Bates",
      "status": "OUT",
      "details": "T. Bates (Out)"
    },
    {
      "name": "C. Johnson",
      "status": "OUT",
      "details": "C. Johnson (Out)"
    },
    {
      "name": "N. Jokic",
      "status": "OUT",
      "details": "N. Jokic (Out)"
    },
    {
      "name": "S. Jones",
      "status": "OUT",
      "details": "S. Jones (Out)"
    },
    {
      "name": "J. Murray",
      "status": "OUT",
      "details": "J. Murray (Out)"
    },
    {
      "name": "J. Valanciunas",
      "status": "OUT",
      "details": "J. Valanciunas (Out)"
    }
  ],
  "DEN": [
    {
      "name": "T. Bates",
      "status": "OUT",
      "details": "T. Bates (Out)"
    },
    {
      "name": "C. Johnson",
      "status": "OUT",
      "details": "C. Johnson (Out)"
    },
    {
      "name": "N. Jokic",
      "status": "OUT",
      "details": "N. Jokic (Out)"
    },
    {
      "name": "S. Jones",
      "status": "OUT",
      "details": "S. Jones (Out)"
    },
    {
      "name": "J. Murray",
      "status": "OUT",
      "details": "J. Murray (Out)"
    },
    {
      "name": "J. Valanciunas",
      "status": "OUT",
      "details": "J. Valanciunas (Out)"
    }
  ],
  "NYK": [
    {
      "name": "Josh Hart",
      "status": "OUT",
      "details": "Josh Hart (Out)"
    },
    {
      "name": "L. Shamet",
      "status": "OUT",
      "details": "L. Shamet (Out)"
    },
    {
      "name": "G. Yabusele",
      "status": "OUT",
      "details": "G. Yabusele (Out)"
    },
    {
      "name": "J. Bouyea",
      "status": "OUT",
      "details": "J. Bouyea (Out)"
    },
    {
      "name": "J. Green",
      "status": "OUT",
      "details": "J. Green (Out)"
    }
  ],
  "PHX": [
    {
      "name": "J. Bouyea",
      "status": "OUT",
      "details": "J. Bouyea (Out)"
    },
    {
      "name": "J. Green",
      "status": "OUT",
      "details": "J. Green (Out)"
    }
  ],
  "SAC": [
    {
      "name": "K. Murray",
      "status": "OUT",
      "details": "K. Murray (Out)"
    },
    {
      "name": "D. Sabonis",
      "status": "OUT",
      "details": "D. Sabonis (Out)"
    },
    {
      "name": "Seth Curry",
      "status": "OUT",
      "details": "Seth Curry (Out)"
    }
  ],
  "GSW": [
    {
      "name": "Seth Curry",
      "status": "OUT",
      "details": "Seth Curry (Out)"
    }
  ],
  "HOU": [
    {
      "name": "I. Crawford",
      "status": "OUT",
      "details": "I. Crawford (Out)"
    },
    {
      "name": "A. Sengun",
      "status": "OUT",
      "details": "A. Sengun (Out)"
    },
    {
      "name": "F. VanVleet",
      "status": "OUT",
      "details": "F. VanVleet (Out)"
    },
    {
      "name": "D. Lillard",
      "status": "OFS",
      "details": "D. Lillard (OFS)"
    },
    {
      "name": "J. Grant",
      "status": "OUT",
      "details": "J. Grant (Out)"
    },
    {
      "name": "S. Henderson",
      "status": "OUT",
      "details": "S. Henderson (Out)"
    },
    {
      "name": "J. Holiday",
      "status": "OUT",
      "details": "J. Holiday (Out)"
    },
    {
      "name": "K. Murray",
      "status": "OUT",
      "details": "K. Murray (Out)"
    },
    {
      "name": "M. Thybulle",
      "status": "OUT",
      "details": "M. Thybulle (Out)"
    },
    {
      "name": "B. Wesley",
      "status": "OUT",
      "details": "B. Wesley (Out)"
    }
  ],
  "POR": [
    {
      "name": "D. Lillard",
      "status": "OFS",
      "details": "D. Lillard (OFS)"
    },
    {
      "name": "J. Grant",
      "status": "OUT",
      "details": "J. Grant (Out)"
    },
    {
      "name": "S. Henderson",
      "status": "OUT",
      "details": "S. Henderson (Out)"
    },
    {
      "name": "J. Holiday",
      "status": "OUT",
      "details": "J. Holiday (Out)"
    },
    {
      "name": "K. Murray",
      "status": "OUT",
      "details": "K. Murray (Out)"
    },
    {
      "name": "M. Thybulle",
      "status": "OUT",
      "details": "M. Thybulle (Out)"
    },
    {
      "name": "B. Wesley",
      "status": "OUT",
      "details": "B. Wesley (Out)"
    }
  ],
  "MIL": [
    {
      "name": "T. Prince",
      "status": "OUT",
      "details": "T. Prince (Out)"
    },
    {
      "name": "R. Hachimura",
      "status": "OUT",
      "details": "R. Hachimura (Out)"
    },
    {
      "name": "A. Reaves",
      "status": "OUT",
      "details": "A. Reaves (Out)"
    },
    {
      "name": "A. Thiero",
      "status": "OUT",
      "details": "A. Thiero (Out)"
    }
  ],
  "LAL": [
    {
      "name": "R. Hachimura",
      "status": "OUT",
      "details": "R. Hachimura (Out)"
    },
    {
      "name": "A. Reaves",
      "status": "OUT",
      "details": "A. Reaves (Out)"
    },
    {
      "name": "A. Thiero",
      "status": "OUT",
      "details": "A. Thiero (Out)"
    }
  ],
  "PHI": [
    {
      "name": "C. Castleton",
      "status": "OUT",
      "details": "C. Castleton (Out)"
    },
    {
      "name": "T. da Silva",
      "status": "OUT",
      "details": "T. da Silva (Out)"
    },
    {
      "name": "J. Suggs",
      "status": "OUT",
      "details": "J. Suggs (Out)"
    },
    {
      "name": "M. Wagner",
      "status": "OUT",
      "details": "M. Wagner (Out)"
    },
    {
      "name": "F. Wagner",
      "status": "OUT",
      "details": "F. Wagner (Out)"
    }
  ]
}