{
  "asof_date": "2026-04-21",
  "built_at_utc": "2026-04-22T01:29:37Z",
  "source": "rotowire",
  "PHI": [
    {
      "name": "J. Embiid",
      "status": "OUT",
      "details": "J. Embiid (Out)"
    },
    {
      "name": "Probable Pitchers",
      "status": "PROB",
      "details": "Probable Pitchers (Prob)"
    }
  ],
  "POR": [
    {
      "name": "D. Lillard",
      "status": "OFS",
      "details": "D. Lillard (OFS)"
    },
    {
      "name": "V. Wembanyama",
      "status": "QUES",
      "details": "V. Wembanyama (Ques)"
    },
    {
      "name": "D. Jones Garcia",
      "status": "OFS",
      "details": "D. Jones Garcia (OFS)"
    },
    {
      "name": "J. McLaughlin",
      "status": "OUT",
      "details": "J. McLaughlin (Out)"
    }
  ],
  "SAS": [
    {
      "name": "D. Jones Garcia",
      "status": "OFS",
      "details": "D. Jones Garcia (OFS)"
    },
    {
      "name": "V. Wembanyama",
      "status": "QUES",
      "details": "V. Wembanyama (Ques)"
    },
    {
      "name": "J. McLaughlin",
      "status": "OUT",
      "details": "J. McLaughlin (Out)"
    }
  ],
  "HOU": [
    {
      "name": "S. Adams",
      "status": "OFS",
      "details": "S. Adams (OFS)"
    },
    {
      "name": "F. VanVleet",
      "status": "OUT",
      "details": "F. VanVleet (Out)"
    },
    {
      "name": "L. Doncic",
      "status": "OUT",
      "details": "L. Doncic (Out)"
    },
    {
      "name": "A. Reaves",
      "status": "OUT",
      "details": "A. Reaves (Out)"
    }
  ],
  "LAL": [
    {
      "name": "L. Doncic",
      "status": "OUT",
      "details": "L. Doncic (Out)"
    },
    {
      "name": "A. Reaves",
      "status": "OUT",
      "details": "A. Reaves (Out)"
    }
  ]
}