{
  "asof_date": "2026-05-01",
  "built_at_utc": "2026-05-02T09:34:32Z",
  "coinflips": [],
  "favorites": [
    {
      "abs_prob_diff": 0.21640648913376187,
      "away_abbrev": "DET",
      "away_ml": -170.0,
      "away_prob": 0.6296296296296297,
      "away_score": 93,
      "away_team": "Detroit Pistons",
      "dog_side": "HOME",
      "fav_side": "AWAY",
      "favorite_prob": 0.6296296296296297,
      "game_id": 401869417,
      "home_abbrev": "ORL",
      "home_ml": 142.0,
      "home_prob": 0.4132231404958678,
      "home_score": 79,
      "home_team": "Orlando Magic",
      "is_coinflip": false,
      "loser_abbrev": "ORL",
      "loser_ml": 142.0,
      "loser_score": 79,
      "loser_side": "HOME",
      "loser_team": "Orlando Magic",
      "underdog_prob": 0.4132231404958678,
      "winner_abbrev": "DET",
      "winner_ml": -170.0,
      "winner_score": 93,
      "winner_side": "AWAY",
      "winner_team": "Detroit Pistons"
    }
  ],
  "summary": {
    "coinflips_total": 0,
    "favorites_lost": 2,
    "favorites_won": 1,
    "games_total": 3
  },
  "underdogs": [
    {
      "abs_prob_diff": 0.2282003710575139,
      "away_abbrev": "CLE",
      "away_ml": -175.0,
      "away_prob": 0.6363636363636364,
      "away_score": 110,
      "away_team": "Cleveland Cavaliers",
      "dog_side": "HOME",
      "fav_side": "AWAY",
      "favorite_prob": 0.6363636363636364,
      "game_id": 401869381,
      "home_abbrev": "TOR",
      "home_ml": 145.0,
      "home_prob": 0.40816326530612246,
      "home_score": 112,
      "home_team": "Toronto Raptors",
      "is_coinflip": false,
      "loser_abbrev": "CLE",
      "loser_ml": -175.0,
      "loser_score": 110,
      "loser_side": "AWAY",
      "loser_team": "Cleveland Cavaliers",
      "underdog_prob": 0.40816326530612246,
      "winner_abbrev": "TOR",
      "winner_ml": 145.0,
      "winner_score": 112,
      "winner_side": "HOME",
      "winner_team": "Toronto Raptors"
    },
    {
      "abs_prob_diff": 0.19459179712770092,
      "away_abbrev": "LAL",
      "away_ml": 136.0,
      "away_prob": 0.423728813559322,
      "away_score": 98,
      "away_team": "Los Angeles Lakers",
      "dog_side": "AWAY",
      "fav_side": "HOME",
      "favorite_prob": 0.6183206106870229,
      "game_id": 401869409,
      "home_abbrev": "HOU",
      "home_ml": -162.0,
      "home_prob": 0.6183206106870229,
      "home_score": 78,
      "home_team": "Houston Rockets",
      "is_coinflip": false,
      "loser_abbrev": "HOU",
      "loser_ml": -162.0,
      "loser_score": 78,
      "loser_side": "HOME",
      "loser_team": "Houston Rockets",
      "underdog_prob": 0.423728813559322,
      "winner_abbrev": "LAL",
      "winner_ml": 136.0,
      "winner_score": 98,
      "winner_side": "AWAY",
      "winner_team": "Los Angeles Lakers"
    }
  ]
}